README.md
setup.py
distributions_me/Binomialdistribution.py
distributions_me/Gaussiandistribution.py
distributions_me/Generaldistribution.py
distributions_me/__init__.py
distributions_me.egg-info/PKG-INFO
distributions_me.egg-info/SOURCES.txt
distributions_me.egg-info/dependency_links.txt
distributions_me.egg-info/not-zip-safe
distributions_me.egg-info/top_level.txt